parametergrouptotf/__init__.py
parametergrouptotf/__main__.py
parametergrouptotf/convert.py
aws_rds_parameter_group_to_tf-1.3.1.dist-info/METADATA
aws_rds_parameter_group_to_tf-1.3.1.dist-info/WHEEL
aws_rds_parameter_group_to_tf-1.3.1.dist-info/entry_points.txt
aws_rds_parameter_group_to_tf-1.3.1.dist-info/top_level.txt
aws_rds_parameter_group_to_tf-1.3.1.dist-info/RECORD
