Metadata-Version: 2.1
Name: aws-rds-parameter-group-to-tf
Version: 1.3.1
Summary: Create a Terraform parameter group from an AWS RDS parameter group.
Home-page: https://github.com/levkk/aws-rds-parameter-group-to-tf
Author: Lev Kokotov
Author-email: lev.kokotov@instacart.com
License: UNKNOWN
Platform: UNKNOWN
Classifier: Programming Language :: Python :: 3
Classifier: License :: OSI Approved :: MIT License
Classifier: Operating System :: OS Independent
Requires-Python: >=3
Requires-Dist: Click (>=7.0)
